pyepisuite/__init__.py
pyepisuite/api_client.py
pyepisuite/dataframe_utils.py
pyepisuite/expdata.py
pyepisuite/models.py
pyepisuite/usetox_input.py
pyepisuite/utils.py
pyepisuite-1.0.1.dist-info/licenses/LICENSE
pyepisuite-1.0.1.dist-info/METADATA
pyepisuite-1.0.1.dist-info/WHEEL
pyepisuite-1.0.1.dist-info/top_level.txt
pyepisuite-1.0.1.dist-info/RECORD
