Metadata-Version: 2.4
Name: pyepisuite
Version: 1.0.1
Summary: A comprehensive Python client for EPA's EPISuite API with DataFrame utilities for environmental chemistry research.
Author-email: "Ali A. Eftekhari" <e.eftekhari@gmail.com>
License: MIT
Project-URL: Homepage, https://github.com/USEtox/PyEPISuite
Project-URL: Documentation, https://usetox.github.io/PyEPISuite/
Project-URL: Repository, https://github.com/USEtox/PyEPISuite
Project-URL: Bug Tracker, https://github.com/USEtox/PyEPISuite/issues
Classifier: Development Status :: 5 - Production/Stable
Classifier: Intended Audience :: Science/Research
Classifier: Intended Audience :: Developers
Classifier: Topic :: Scientific/Engineering :: Chemistry
Classifier: Topic :: Scientific/Engineering :: Information Analysis
Classifier: Programming Language :: Python :: 3
Classifier: Programming Language :: Python :: 3.10
Classifier: Programming Language :: Python :: 3.11
Classifier: Programming Language :: Python :: 3.12
Classifier: License :: OSI Approved :: MIT License
Classifier: Operating System :: OS Independent
Requires-Python: >=3.10
License-File: LICENSE
Requires-Dist: requests
Requires-Dist: dacite
Requires-Dist: pandas>=1.5.0
Requires-Dist: openpyxl>=3.0.0
Provides-Extra: docs
Requires-Dist: mkdocs>=1.5.0; extra == "docs"
Requires-Dist: mkdocs-material>=9.0.0; extra == "docs"
Requires-Dist: mkdocstrings[python]>=0.20.0; extra == "docs"
Provides-Extra: dev
Requires-Dist: pytest>=7.0.0; extra == "dev"
Requires-Dist: pytest-cov>=4.0.0; extra == "dev"
Requires-Dist: black>=23.0.0; extra == "dev"
Requires-Dist: isort>=5.0.0; extra == "dev"
Requires-Dist: mypy>=1.0.0; extra == "dev"
Requires-Dist: flake8>=6.0.0; extra == "dev"
Dynamic: license-file
